[
{"id":1,"name":"杯装之诗","state":0,"isNew":false},
{"id":2,"name":"暂别冬都","state":1,"isNew":false},
{"id":3,"name":"陵薮市朝","state":2,"isNew":false},
{"id":4,"name":"深秘之息","state":3,"isNew":false},
{"id":5,"name":"浮生孰来","state":4,"isNew":false},
{"id":6,"name":"烟火之邀","state":0,"isNew":false},
{"id":7,"name":"鱼龙灯昼","state":1,"isNew":false},
{"id":8,"name":"赤团开时","state":2,"isNew":false},
{"id":9,"name":"叶落风随","state":3,"isNew":false},
{"id":10,"name":"焰色天河","state":4,"isNew":false},
{"id":11,"name":"鬼门斗宴","state":0,"isNew":false},
{"id":12,"name":"出尘入世","state":1,"isNew":false},
{"id":13,"name":"华紫樱绯","state":2,"isNew":false},
{"id":14,"name":"苍流踏花","state":3,"isNew":false},
{"id":15,"name":"雳裁冥昭","state":4,"isNew":false},
{"id":16,"name":"月草的赐慧","state":0,"isNew":false},
{"id":17,"name":"余火变相","state":1,"isNew":false},
{"id":18,"name":"敕诫枢谋","state":2,"isNew":false},
{"id":19,"name":"烈阳烁金","state":3,"isNew":false},
{"id":20,"name":"心珠循琅","state":4,"isNew":true},
{"id":21,"name":"渊海界令","state":0,"isNew":false},
{"id":22,"name":"劫中泛滥","state":1,"isNew":false},
{"id":23,"name":"众水的颂诗","state":2,"isNew":true},
{"id":24,"name":"光与影的戏术","state":3,"isNew":false},
{"id":25,"name":"浮岳虹珠","state":4,"isNew":false},
{"id":26,"name":"浪涌之瞬","state":0,"isNew":false}
]